postfinance/__init__.py
postfinance/config.py
postfinance/exceptions.py
postfinance/payments.py
postfinance/postfinance.py
postfinance/utils.py
postfinance/constants/__init__.py
postfinance/constants/env.py
postfinance/constants/error_code.py
postfinance/constants/sha_in.py
postfinance-0.1.2.dist-info/LICENSE
postfinance-0.1.2.dist-info/METADATA
postfinance-0.1.2.dist-info/WHEEL
postfinance-0.1.2.dist-info/top_level.txt
postfinance-0.1.2.dist-info/RECORD
